inapppy/__init__.py
inapppy/appstore.py
inapppy/errors.py
inapppy/googleplay.py
inapppy/asyncio/__init__.py
inapppy/asyncio/appstore.py
inapppy-2.4.dist-info/LICENSE
inapppy-2.4.dist-info/METADATA
inapppy-2.4.dist-info/WHEEL
inapppy-2.4.dist-info/top_level.txt
inapppy-2.4.dist-info/RECORD
