Metadata-Version: 2.1
Name: inapppy
Version: 2.4
Summary: In-app purchase validation library for Apple AppStore and GooglePlay.
Home-page: https://github.com/dotpot/InAppPy
Author: Lukas Šalkauskas
Author-email: halfas.online@gmail.com
License: MIT
Keywords: in-app store purchase googleplay appstore validation
Platform: UNKNOWN
Requires-Dist: aiohttp
Requires-Dist: rsa
Requires-Dist: requests
Requires-Dist: google-api-python-client
Requires-Dist: oauth2client (==3.0.0)
